modwsgideploy/__init__.py
modwsgideploy/cli.py
modwsgideploy/cookiecutter.json
modwsgideploy/build/lib/modwsgideploy/__init__.py
modwsgideploy/build/lib/modwsgideploy/cli.py
modwsgideploy/build/lib/modwsgideploy/cookiecutter.json
modwsgideploy/build/lib/modwsgideploy/hooks/post_gen_project.py
modwsgideploy/build/lib/modwsgideploy/hooks/pre_gen_project.py
modwsgideploy/build/lib/modwsgideploy/{{cookiecutter.folder_name}}/README.txt
modwsgideploy/build/lib/modwsgideploy/{{cookiecutter.folder_name}}/__init__.py
modwsgideploy/build/lib/modwsgideploy/{{cookiecutter.folder_name}}/test.wsgi
modwsgideploy/build/lib/modwsgideploy/{{cookiecutter.folder_name}}/{{cookiecutter.package_name}}.conf
modwsgideploy/build/lib/modwsgideploy/{{cookiecutter.folder_name}}/{{cookiecutter.package_name}}.wsgi
modwsgideploy/build/lib.linux-x86_64-2.7/modwsgideploy/__init__.py
modwsgideploy/build/lib.linux-x86_64-2.7/modwsgideploy/cli.py
modwsgideploy/build/lib.linux-x86_64-2.7/modwsgideploy/cookiecutter.json
modwsgideploy/build/lib.linux-x86_64-2.7/modwsgideploy/hooks/post_gen_project.py
modwsgideploy/build/lib.linux-x86_64-2.7/modwsgideploy/hooks/pre_gen_project.py
modwsgideploy/build/lib.linux-x86_64-2.7/modwsgideploy/{{cookiecutter.folder_name}}/README.txt
modwsgideploy/build/lib.linux-x86_64-2.7/modwsgideploy/{{cookiecutter.folder_name}}/__init__.py
modwsgideploy/build/lib.linux-x86_64-2.7/modwsgideploy/{{cookiecutter.folder_name}}/test.wsgi
modwsgideploy/build/lib.linux-x86_64-2.7/modwsgideploy/{{cookiecutter.folder_name}}/{{cookiecutter.package_name}}.conf
modwsgideploy/build/lib.linux-x86_64-2.7/modwsgideploy/{{cookiecutter.folder_name}}/{{cookiecutter.package_name}}.wsgi
modwsgideploy/hooks/post_gen_project.py
modwsgideploy/hooks/pre_gen_project.py
modwsgideploy/modwsgideploy.egg-info/SOURCES.txt
modwsgideploy/modwsgideploy.egg-info/dependency_links.txt
modwsgideploy/modwsgideploy.egg-info/entry_points.txt
modwsgideploy/modwsgideploy.egg-info/requires.txt
modwsgideploy/modwsgideploy.egg-info/top_level.txt
modwsgideploy/{{cookiecutter.folder_name}}/README.txt
modwsgideploy/{{cookiecutter.folder_name}}/__init__.py
modwsgideploy/{{cookiecutter.folder_name}}/test.wsgi
modwsgideploy-3.18.20.dist-info/METADATA
modwsgideploy-3.18.20.dist-info/RECORD
modwsgideploy-3.18.20.dist-info/WHEEL
modwsgideploy-3.18.20.dist-info/entry_points.txt
modwsgideploy-3.18.20.dist-info/top_level.txt
