Metadata-Version: 2.1
Name: modwsgideploy
Version: 3.18.20
Summary: Deploy Pyramid via apache2 and modwsgi.
Home-page: http://lucasmanual.com/mywiki/modwsgideploy
Author: Lukasz Szybalski
Author-email: szybalski@gmail.com
License: BSD
Keywords: apache2 modwsgi/libapache2-mod-wsgi-py3 pyramid deploy script
Platform: UNKNOWN
Classifier: Development Status :: 5 - Production/Stable
Classifier: Intended Audience :: Developers
Classifier: License :: OSI Approved :: BSD License
Classifier: Natural Language :: English
Classifier: Programming Language :: Python :: 2
Classifier: Programming Language :: Python :: 2.6
Classifier: Programming Language :: Python :: 2.7
Classifier: Programming Language :: Python :: 3
Requires-Dist: cookiecutter (>=1.5)
Requires-Dist: mako
Requires-Dist: Click (>=6.0)
